{
    "info": {
        "_postman_id": "b1a2b3c4-d5e6-f7g8-h9i0-j1k2l3m4n5o6",
        "name": "Offline-First Todo API",
        "description": "Collection for testing the Node.js Offline-First Todo API",
        "schema": "https://schema.getpostman.com/json/collection/v2.1.0/collection.json"
    },
    "item": [
        {
            "name": "Get Active Todos",
            "request": {
                "method": "GET",
                "header": [],
                "url": {
                    "raw": "{{baseUrl}}/api/todos",
                    "host": [
                        "{{baseUrl}}"
                    ],
                    "path": [
                        "api",
                        "todos"
                    ]
                }
            },
            "response": []
        },
        {
            "name": "Create Todo",
            "request": {
                "method": "POST",
                "header": [
                    {
                        "key": "Content-Type",
                        "value": "application/json",
                        "type": "text"
                    }
                ],
                "body": {
                    "mode": "raw",
                    "raw": "{\n    \"syncId\": \"550e8400-e29b-41d4-a716-446655440000\",\n    \"title\": \"Buy groceries\",\n    \"description\": \"Milk, eggs, bread\"\n}"
                },
                "url": {
                    "raw": "{{baseUrl}}/api/todos",
                    "host": [
                        "{{baseUrl}}"
                    ],
                    "path": [
                        "api",
                        "todos"
                    ]
                }
            },
            "response": []
        },
        {
            "name": "Sync Todos (Get Changes)",
            "request": {
                "method": "GET",
                "header": [],
                "url": {
                    "raw": "{{baseUrl}}/api/todos/sync?since=2023-01-01T00:00:00.000Z",
                    "host": [
                        "{{baseUrl}}"
                    ],
                    "path": [
                        "api",
                        "todos",
                        "sync"
                    ],
                    "query": [
                        {
                            "key": "since",
                            "value": "2023-01-01T00:00:00.000Z",
                            "description": "Timestamp to fetch changes after"
                        }
                    ]
                }
            },
            "response": []
        },
        {
            "name": "Update Todo",
            "request": {
                "method": "PATCH",
                "header": [
                    {
                        "key": "Content-Type",
                        "value": "application/json",
                        "type": "text"
                    }
                ],
                "body": {
                    "mode": "raw",
                    "raw": "{\n    \"isCompleted\": true\n}"
                },
                "url": {
                    "raw": "{{baseUrl}}/api/todos/:syncId",
                    "host": [
                        "{{baseUrl}}"
                    ],
                    "path": [
                        "api",
                        "todos",
                        ":syncId"
                    ],
                    "variable": [
                        {
                            "key": "syncId",
                            "value": "550e8400-e29b-41d4-a716-446655440000",
                            "description": "Client-generated sync ID (UUID v4)"
                        }
                    ]
                }
            },
            "response": []
        },
        {
            "name": "Soft Delete Todo",
            "request": {
                "method": "DELETE",
                "header": [],
                "url": {
                    "raw": "{{baseUrl}}/api/todos/:syncId",
                    "host": [
                        "{{baseUrl}}"
                    ],
                    "path": [
                        "api",
                        "todos",
                        ":syncId"
                    ],
                    "variable": [
                        {
                            "key": "syncId",
                            "value": "550e8400-e29b-41d4-a716-446655440000",
                            "description": "Client-generated sync ID (UUID v4)"
                        }
                    ]
                }
            },
            "response": []
        }
    ],
    "event": [
        {
            "listen": "prerequest",
            "script": {
                "type": "text/javascript",
                "exec": [
                    ""
                ]
            }
        },
        {
            "listen": "test",
            "script": {
                "type": "text/javascript",
                "exec": [
                    ""
                ]
            }
        }
    ],
    "variable": [
        {
            "key": "baseUrl",
            "value": "http://localhost:3000",
            "type": "string"
        }
    ]
}